pusion/__init__.py
pusion/auto/__init__.py
pusion/auto/auto_combiner.py
pusion/auto/detector.py
pusion/auto/generic_combiner.py
pusion/control/__init__.py
pusion/control/decision_processor.py
pusion/core/__init__.py
pusion/core/behaviour_knowledge_space_combiner.py
pusion/core/borda_count_combiner.py
pusion/core/combiner.py
pusion/core/complementary_output_combiner.py
pusion/core/cosine_similarity_combiner.py
pusion/core/decision_templates_combiner.py
pusion/core/dempster_shafer_combiner.py
pusion/core/k_nearest_neighbors_combiner.py
pusion/core/macro_majority_vote_combiner.py
pusion/core/maximum_likelihood_combiner.py
pusion/core/micro_majority_vote_combiner.py
pusion/core/naive_bayes_combiner.py
pusion/core/neural_network_combiner.py
pusion/core/simple_average_combiner.py
pusion/core/weighted_voting_combiner.py
pusion/evaluation/__init__.py
pusion/evaluation/evaluation.py
pusion/evaluation/evaluation_metrics.py
pusion/input_output/__init__.py
pusion/input_output/file_input_output.py
pusion/model/__init__.py
pusion/model/configuration.py
pusion/model/report.py
pusion/util/__init__.py
pusion/util/constants.py
pusion/util/ensemble.py
pusion/util/exceptions.py
pusion/util/generator.py
pusion/util/processes.py
pusion/util/transformer.py
pusion-0.2.0.dist-info/LICENSE
pusion-0.2.0.dist-info/METADATA
pusion-0.2.0.dist-info/WHEEL
pusion-0.2.0.dist-info/top_level.txt
pusion-0.2.0.dist-info/RECORD
