Metadata-Version: 2.1
Name: pusion
Version: 0.2.0
Summary: Pusion (Python Universal Fusion) is a generic and automated framework for decision fusion written in Python.
Author: Admir Obralija
Author-email: Yannick Wilhelm <yannick.wilhelm@gsame.uni-stuttgart.de>
License: MIT License
Project-URL: homepage, https://github.com/IPVS-AS/pusion
Project-URL: documentation, https://ipvs-as.github.io/pusion/build/html/index.html
Project-URL: Bug Tracker, https://github.com/IPVS-AS/pusion/issues
Keywords: decision fusion,combining classifiers,fusion,pusion
Classifier: Programming Language :: Python :: 3
Classifier: License :: OSI Approved :: MIT License
Classifier: Operating System :: OS Independent
Requires-Python: >=3.6
License-File: LICENSE
Requires-Dist: numpy (~=1.20.2)
Requires-Dist: scipy (~=1.6.2)
Requires-Dist: scikit-learn (~=0.24.1)
Requires-Dist: setuptools (~=54.2.0)
Requires-Dist: pandas (~=1.2.3)
Requires-Dist: matplotlib (~=3.4.1)
Requires-Dist: torchmetrics (~=0.7.2)
Provides-Extra: doc
Requires-Dist: sphinx ; extra == 'doc'
Provides-Extra: test
Requires-Dist: pytest (>5.0.0) ; extra == 'test'
